microtrax/__init__.py
microtrax/cli.py
microtrax/constants.py
microtrax/core.py
microtrax/dashboard.py
microtrax/enums.py
microtrax/io_utils.py
microtrax/backend/__init__.py
microtrax/backend/app.py
microtrax/backend/domain/__init__.py
microtrax/backend/domain/schemas.py
microtrax/backend/routers/__init__.py
microtrax/backend/routers/experiments.py
microtrax/backend/routers/images.py
microtrax/backend/routers/plots.py
microtrax/backend/routers/text.py
microtrax/backend/services/__init__.py
microtrax/backend/services/experiment_service.py
microtrax/backend/services/frontend_service.py
microtrax/backend/services/plot_service.py
microtrax/backend/services/text_service.py
microtrax/frontend/build/asset-manifest.json
microtrax/frontend/build/index.html
microtrax/frontend/build/static/css/main.c04f8655.css
microtrax/frontend/build/static/js/main.77e51d58.js
microtrax/frontend/build/static/js/main.77e51d58.js.LICENSE.txt
microtrax/frontend/node_modules/flatted/python/flatted.py
microtrax/frontend/node_modules/shell-quote/print.py
microtrax/tests/__init__.py
microtrax/tests/conftest.py
microtrax/tests/test_backend.py
microtrax/tests/test_core.py
microtrax/tests/test_enums.py
microtrax-0.1.7.dist-info/licenses/LICENSE.md
microtrax-0.1.7.dist-info/METADATA
microtrax-0.1.7.dist-info/WHEEL
microtrax-0.1.7.dist-info/entry_points.txt
microtrax-0.1.7.dist-info/top_level.txt
microtrax-0.1.7.dist-info/RECORD
