Metadata-Version: 2.4
Name: microtrax
Version: 0.1.7
Summary: Local-first, minimalist, micro experiment tracking for Machine Learning/Deep Learning workflows
Author: microtrax
License: MIT
Classifier: Development Status :: 3 - Alpha
Classifier: Intended Audience :: Developers
Classifier: Intended Audience :: Science/Research
Classifier: License :: OSI Approved :: MIT License
Classifier: Operating System :: OS Independent
Classifier: Programming Language :: Python :: 3
Classifier: Programming Language :: Python :: 3.8
Classifier: Programming Language :: Python :: 3.9
Classifier: Programming Language :: Python :: 3.10
Classifier: Programming Language :: Python :: 3.11
Classifier: Topic :: Scientific/Engineering :: Artificial Intelligence
Requires-Python: >=3.8
License-File: LICENSE.md
Requires-Dist: numpy
Requires-Dist: matplotlib
Requires-Dist: plotly>=5.0.0
Requires-Dist: pandas
Requires-Dist: fastapi
Requires-Dist: uvicorn[standard]
Requires-Dist: psutil
Requires-Dist: pillow
Provides-Extra: gpu
Requires-Dist: nvidia-ml-py3; extra == "gpu"
Provides-Extra: dev
Requires-Dist: pytest; extra == "dev"
Requires-Dist: pytest-cov; extra == "dev"
Requires-Dist: ruff; extra == "dev"
Dynamic: license-file
